record_batcher/__init__.py
record_batcher/record_batcher.py
record_batcher-0.1.0.dist-info/LICENSE
record_batcher-0.1.0.dist-info/METADATA
record_batcher-0.1.0.dist-info/WHEEL
record_batcher-0.1.0.dist-info/RECORD
